kleister/__init__.py
kleister/api/__init__.py
kleister/api/auth_api.py
kleister/api/fabric_api.py
kleister/api/forge_api.py
kleister/api/group_api.py
kleister/api/minecraft_api.py
kleister/api/mod_api.py
kleister/api/neoforge_api.py
kleister/api/pack_api.py
kleister/api/profile_api.py
kleister/api/quilt_api.py
kleister/api/user_api.py
kleister/api_client.py
kleister/api_response.py
kleister/configuration.py
kleister/exceptions.py
kleister/models/__init__.py
kleister/models/attach_build_to_version_request.py
kleister/models/attach_minecraft_to_build_request.py
kleister/models/auth_token.py
kleister/models/auth_verify.py
kleister/models/build.py
kleister/models/build_version.py
kleister/models/create_build_request.py
kleister/models/create_group_request.py
kleister/models/create_mod_request.py
kleister/models/create_pack_request.py
kleister/models/create_user_request.py
kleister/models/create_version_request.py
kleister/models/delete_group_from_mod_request.py
kleister/models/delete_group_from_pack_request.py
kleister/models/delete_pack_from_group_request.py
kleister/models/delete_pack_from_user_request.py
kleister/models/fabric.py
kleister/models/forge.py
kleister/models/group.py
kleister/models/group_mod.py
kleister/models/group_pack.py
kleister/models/list_build_versions200_response.py
kleister/models/list_builds200_response.py
kleister/models/list_fabric_builds200_response.py
kleister/models/list_fabrics200_response.py
kleister/models/list_forge_builds200_response.py
kleister/models/list_forges200_response.py
kleister/models/list_group_mods200_response.py
kleister/models/list_group_packs200_response.py
kleister/models/list_group_users200_response.py
kleister/models/list_groups200_response.py
kleister/models/list_minecraft_builds200_response.py
kleister/models/list_minecrafts200_response.py
kleister/models/list_mod_groups200_response.py
kleister/models/list_mod_users200_response.py
kleister/models/list_mods200_response.py
kleister-2.1.1.dist-info/METADATA
kleister-2.1.1.dist-info/WHEEL
kleister-2.1.1.dist-info/licenses/LICENSE
kleister-2.1.1.dist-info/RECORD
